objdump/__init__.py
objdump/base.py
objdump-0.0.1.data/data/README.md/README.md
objdump-0.0.1.dist-info/LICENSE
objdump-0.0.1.dist-info/METADATA
objdump-0.0.1.dist-info/WHEEL
objdump-0.0.1.dist-info/entry_points.txt
objdump-0.0.1.dist-info/top_level.txt
objdump-0.0.1.dist-info/RECORD
