Metadata-Version: 2.1
Name: objdump
Version: 0.0.1
Summary: interact with objdump command
Home-page: https://github.com/ramwin/objdump
Author: Xiang Wang
Author-email: ramwin@qq.com
License: MIT
Keywords: objdump
Platform: UNKNOWN
Classifier: License :: OSI Approved :: MIT License
Classifier: Programming Language :: Python :: 3
License-File: LICENSE
Provides-Extra: dev
Provides-Extra: test
